ibm_data_engine/__init__.py
ibm_data_engine/data_engine_offline_store.py
ibm_data_engine-0.4.0.dist-info/LICENSE
ibm_data_engine-0.4.0.dist-info/METADATA
ibm_data_engine-0.4.0.dist-info/WHEEL
ibm_data_engine-0.4.0.dist-info/RECORD
