Metadata-Version: 2.1
Name: ibm-data-engine
Version: 0.4.0
Summary: Feast offline feature store implementation backed by the IBM Cloud Data Engine
Home-page: https://github.com/IBM/feast-ibm
License: Apache-2.0
Author: Michal Siedlaczek
Author-email: michal.siedlaczek@ibm.com
Maintainer: Michal Siedlaczek
Maintainer-email: michal.siedlaczek@ibm.com
Requires-Python: >=3.9,<3.12
Classifier: Development Status :: 2 - Pre-Alpha
Classifier: Environment :: Plugins
Classifier: Intended Audience :: Developers
Classifier: License :: OSI Approved :: Apache Software License
Classifier: Operating System :: OS Independent
Classifier: Programming Language :: Python
Classifier: Programming Language :: Python :: 3
Classifier: Programming Language :: Python :: 3.9
Classifier: Programming Language :: Python :: 3.10
Classifier: Programming Language :: Python :: 3.11
Classifier: Programming Language :: Python :: 3.8
Requires-Dist: feast (>=0.40.0,<0.41.0)
Requires-Dist: ibmcloudsql (>=0.5.11,<0.6.0)
Requires-Dist: urllib3 (<2)
Project-URL: Repository, https://github.com/IBM/feast-ibm
